{
    "msg": "",
    "data": [
        {
            "id": 1,
            "uri": "/home",
            "pName": "首页",
            "pIcon": "",
            "parentId": 0,
            "permission": null,
            "children": [
                {
                    "id": 11,
                    "uri": "home",
                    "pName": "首页",
                    "pIcon": null,
                    "parentId": 1,
                    "permission": null,
                    "children": [],
                    "label": null,
                    "rid": 0,
                    "readerCount": 0
                }
            ],
            "label": null,
            "rid": 0,
            "readerCount": 0
        },
        {
            "id": 2,
            "uri": "/nyqxsk",
            "pName": "农业气象实况",
            "pIcon": "",
            "parentId": 0,
            "permission": null,
            "children": [
                {
                    "id": 21,
                    "uri": "nyqxsk",
                    "pName": "农业气象实况",
                    "pIcon": null,
                    "parentId": 2,
                    "permission": null,
                    "children": [],
                    "label": null,
                    "rid": 0,
                    "readerCount": 0
                }
            ],
            "label": null,
            "rid": 0,
            "readerCount": 0
        },
        {
            "id": 3,
            "uri": "/nyqxls",
            "pName": "农业气象历史",
            "pIcon": "",
            "parentId": 0,
            "permission": null,
            "children": [
                {
                    "id": 31,
                    "uri": "nyqxls",
                    "pName": "农业气象历史",
                    "pIcon": null,
                    "parentId": 3,
                    "permission": null,
                    "children": [],
                    "label": null,
                    "rid": 0,
                    "readerCount": 0
                }
            ],
            "label": null,
            "rid": 0,
            "readerCount": 0
        },
        {
            "id": 4,
            "uri": "/nqjcyj",
            "pName": "农情监测预警",
            "pIcon": "",
            "parentId": 0,
            "permission": null,
            "children": [
                {
                    "id": 41,
                    "uri": "nqjcyj",
                    "pName": "农情监测预警",
                    "pIcon": null,
                    "parentId": 3,
                    "permission": null,
                    "children": [],
                    "label": null,
                    "rid": 0,
                    "readerCount": 0
                }
            ],
            "label": null,
            "rid": 0,
            "readerCount": 0
        },
        {
            "id": 5,
            "uri": "/nyqxyzt",
            "pName": "农业气象一张图",
            "pIcon": "",
            "parentId": 0,
            "permission": null,
            "children": [
                {
                    "id": 51,
                    "uri": "nyqxyzt",
                    "pName": "农业气象一张图",
                    "pIcon": null,
                    "parentId": 3,
                    "permission": null,
                    "children": [],
                    "label": null,
                    "rid": 0,
                    "readerCount": 0
                }
            ],
            "label": null,
            "rid": 0,
            "readerCount": 0
        },
        {
            "id": 6,
            "uri": "/grzx",
            "pName": "个人中心",
            "pIcon": "",
            "parentId": 0,
            "permission": null,
            "children": [
                {
                    "id": 61,
                    "uri": "grzx",
                    "pName": "个人中心",
                    "pIcon": null,
                    "parentId": 3,
                    "permission": null,
                    "children": [],
                    "label": null,
                    "rid": 0,
                    "readerCount": 0
                }
            ],
            "label": null,
            "rid": 0,
            "readerCount": 0
        }
    ],
    "success": true
}